odoo/addons/pos_payment_description/README.rst
odoo/addons/pos_payment_description/__init__.py
odoo/addons/pos_payment_description/__manifest__.py
odoo/addons/pos_payment_description/i18n/fr.po
odoo/addons/pos_payment_description/i18n/it.po
odoo/addons/pos_payment_description/i18n/pos_payment_description.pot
odoo/addons/pos_payment_description/models/__init__.py
odoo/addons/pos_payment_description/models/pos_order.py
odoo/addons/pos_payment_description/readme/CONTRIBUTORS.rst
odoo/addons/pos_payment_description/readme/DESCRIPTION.rst
odoo/addons/pos_payment_description/static/description/icon.png
odoo/addons/pos_payment_description/static/description/index.html
odoo/addons/pos_payment_description/static/description/pos_order_tree.png
odoo/addons/pos_payment_description/views/view_pos_order.xml
odoo_addon_pos_payment_description-16.0.1.0.0.4.dist-info/METADATA
odoo_addon_pos_payment_description-16.0.1.0.0.4.dist-info/WHEEL
odoo_addon_pos_payment_description-16.0.1.0.0.4.dist-info/top_level.txt
odoo_addon_pos_payment_description-16.0.1.0.0.4.dist-info/RECORD
